pseudocare/__init__.py
pseudocare/pseudocare.py
pseudocare/providers/__init__.py
pseudocare/providers/custom_date_provider.py
pseudocare/providers/custom_mail_provider.py
pseudocare-0.1.6.dist-info/licenses/LICENSE
pseudocare-0.1.6.dist-info/METADATA
pseudocare-0.1.6.dist-info/WHEEL
pseudocare-0.1.6.dist-info/top_level.txt
pseudocare-0.1.6.dist-info/RECORD
