Metadata-Version: 2.4
Name: pseudocare
Version: 0.1.6
Summary: Pseudonymization of medical reports using a named entity recognition model and the Faker library
Author-email: Youssouf Anis DAHLOUK <ydahlouk@chu-reims.fr>, Rudy MERIEUX <rmerieux@chu-reims.fr>, Seydou KANE <skane@chu-reims.fr>
License: Software PseudoCare - Copyright By Institut de l'Inteligence Artificielle en Santé - License BSD-3-Clause - YEAR 2024-2025
Project-URL: Homepage, https://github.com/IIAS-Research/PseudoCare
Project-URL: Issues, https://github.com/IIAS-Research/PseudoCare/issues
Requires-Python: >=3.10
License-File: LICENSE
Requires-Dist: edsnlp[ml]>=0.15.0
Requires-Dist: faker>=35.2.0
Requires-Dist: pylint>=3.3.4
Requires-Dist: tqdm>=4.67.1
Requires-Dist: unidecode>=1.3.8
Dynamic: license-file
Dynamic: requires-python
